trajopt/__init__.py
trajopt/example.py
trajopt-0.0.1.dist-info/METADATA
trajopt-0.0.1.dist-info/WHEEL
trajopt-0.0.1.dist-info/RECORD
