Metadata-Version: 2.4
Name: trajopt
Version: 0.0.1
Summary: TrajOpt
Author-email: Skye Mceowen <skye@mceowen.io>
Requires-Python: >=3.8
Requires-Dist: setuptools
